{
	"0":  [
		[null, true, true, null],
		[true, null, null, true],
		[true, null, true, true],
		[true, true, null, true],
		[true, null, null, true],
		[null, true, true, null]
	],
	"1":  [
		[null, true, null, null],
		[true, true, null, null],
		[null, true, null, null],
		[null, true, null, null],
		[null, true, null, null],
		[true, true, true, null]
	],
	"2": [
		[null, true, true, null],
		[true, null, null, true],
		[true, null, null, true],
		[null, true, true, null],
		[true, null, null, null],
		[true, true, true, true]
	],
	"3":  [
		[null, true, true, null],
		[true, null, null, true],
		[null, null, true, null],
		[null, null, null, true],
		[true, null, null, true],
		[null, true, true, null]
	],
	"4": [
		[null,null,true,null],
		[null,true,true,null],
		[true,null,true,null],
		[true,true,true,true],
		[null,null,true,null],
		[null,null,true,null]

	],
	"5": [
		[true,true,true,true],
		[true,null,null,null],
		[true,true,true,null],
		[null,null,null,true],
		[true,null,null,true],
		[null,true,true,null]
	],
	"6": [
		[null,true,true,null],
		[true,null,null,null],
		[true,true,true,null],
		[true,null,null,true],
		[true,null,null,true],	
		[null,true,true,null]
	],
	"7": [
		[true,true,true,true],
		[null,null,null,true],
		[null,null,true,null],
		[null,true,null,null],
		[null,true,null,null],
		[null,true,null,null]
	],
	"8":[
		[null,true,true,null],
		[true,null,null,true],
		[null,true,true,null],
		[true,null,null,true],
		[true,null,null,true],	
		[null,true,true,null]
	],
	"9":[
		[null,true,true,null],
		[true,null,null,true],
		[true,null,null,true],
		[null,true,true,true],
		[null,null,null,true],
		[null,true,true,true]
	]
}